{
  "entries": [
    {
      "caught_by": [
        "geometric",
        "oracle",
        "semantic"
      ],
      "entry_id": "8062726_2094792_fact2",
      "score": 0.9443220496177673,
      "source_id": "8062726_2094792",
      "value": " Victoria, Australia"
    },
    {
      "caught_by": [
        "semantic"
      ],
      "entry_id": "15618168_3102813_fact2",
      "score": 0.6299533247947693,
      "source_id": "15618168_3102813",
      "value": " Australian state of Victoria"
    },
    {
      "caught_by": [
        "semantic"
      ],
      "entry_id": "44198967_4249047_fact0",
      "score": 0.6073834896087646,
      "source_id": "44198967_4249047",
      "value": " Australian state of Victoria"
    },
    {
      "caught_by": [
        "semantic"
      ],
      "entry_id": "36206317_2432263_fact0",
      "score": 0.6057581901550293,
      "source_id": "36206317_2432263",
      "value": " Australian state of Victoria"
    },
    {
      "caught_by": [
        "semantic"
      ],
      "entry_id": "35888152_2160841_fact0",
      "score": 0.6049633622169495,
      "source_id": "35888152_2160841",
      "value": " Australian state of Victoria"
    },
    {
      "caught_by": [
        "semantic"
      ],
      "entry_id": "1696175_650352_fact3",
      "score": 0.603884220123291,
      "source_id": "1696175_650352",
      "value": " Victoria, Australia"
    },
    {
      "caught_by": [
        "semantic"
      ],
      "entry_id": "35693393_1997156_fact0",
      "score": 0.6011143922805786,
      "source_id": "35693393_1997156",
      "value": " Australian state of Victoria"
    },
    {
      "caught_by": [
        "semantic"
      ],
      "entry_id": "22811966_2617795_fact2",
      "score": 0.5984921455383301,
      "source_id": "22811966_2617795",
      "value": " Victoria"
    },
    {
      "caught_by": [
        "semantic"
      ],
      "entry_id": "3009353_598040_fact1",
      "score": 0.5971834659576416,
      "source_id": "3009353_598040",
      "value": " the Australian state of Victoria"
    },
    {
      "caught_by": [
        "semantic"
      ],
      "entry_id": "52475580_5350034_fact0",
      "score": 0.5967232584953308,
      "source_id": "52475580_5350034",
      "value": " Australian state of Victoria"
    },
    {
      "caught_by": [
        "semantic"
      ],
      "entry_id": "38769814_4443321_fact0",
      "score": 0.5944396257400513,
      "source_id": "38769814_4443321",
      "value": " Australian state of Victoria"
    },
    {
      "caught_by": [
        "semantic"
      ],
      "entry_id": "44318048_4353518_fact0",
      "score": 0.5927189588546753,
      "source_id": "44318048_4353518",
      "value": " Australian state of Victoria"
    },
    {
      "caught_by": [
        "semantic"
      ],
      "entry_id": "34768117_1347633_fact1",
      "score": 0.5926972031593323,
      "source_id": "34768117_1347633",
      "value": " British colony of Victoria"
    },
    {
      "caught_by": [
        "semantic"
      ],
      "entry_id": "36745169_2871747_fact0",
      "score": 0.5913432240486145,
      "source_id": "36745169_2871747",
      "value": " Australian state of Victoria"
    },
    {
      "caught_by": [
        "semantic"
      ],
      "entry_id": "41654722_4513484_fact0",
      "score": 0.590903639793396,
      "source_id": "41654722_4513484",
      "value": " Australian state of Victoria"
    },
    {
      "caught_by": [
        "semantic"
      ],
      "entry_id": "44307261_4343128_fact0",
      "score": 0.5906820297241211,
      "source_id": "44307261_4343128",
      "value": " Australian state of Victoria"
    },
    {
      "caught_by": [
        "semantic"
      ],
      "entry_id": "28965662_3456656_fact6",
      "score": 0.5895472764968872,
      "source_id": "28965662_3456656",
      "value": " Victoria"
    },
    {
      "caught_by": [
        "semantic"
      ],
      "entry_id": "35431181_1797564_fact0",
      "score": 0.5889608263969421,
      "source_id": "35431181_1797564",
      "value": " Australian state of Victoria"
    },
    {
      "caught_by": [
        "semantic"
      ],
      "entry_id": "49127221_5347242_fact0",
      "score": 0.5875411033630371,
      "source_id": "49127221_5347242",
      "value": " Australian state of Victoria"
    },
    {
      "caught_by": [
        "semantic"
      ],
      "entry_id": "39340767_4972773_fact1",
      "score": 0.5873746275901794,
      "source_id": "39340767_4972773",
      "value": " Australian state of Victoria"
    },
    {
      "caught_by": [
        "semantic"
      ],
      "entry_id": "35900417_2172103_fact0",
      "score": 0.5868616104125977,
      "source_id": "35900417_2172103",
      "value": " Australian state of Victoria"
    },
    {
      "caught_by": [
        "semantic"
      ],
      "entry_id": "1123813_469994_fact1",
      "score": 0.5853779315948486,
      "source_id": "1123813_469994",
      "value": " Australian state of Victoria"
    },
    {
      "caught_by": [
        "semantic"
      ],
      "entry_id": "51508123_4681232_fact0",
      "score": 0.5833001136779785,
      "source_id": "51508123_4681232",
      "value": " Australian state of Victoria"
    },
    {
      "caught_by": [
        "semantic"
      ],
      "entry_id": "40827201_3770639_fact1",
      "score": 0.5791488885879517,
      "source_id": "40827201_3770639",
      "value": " Australia"
    },
    {
      "caught_by": [
        "semantic"
      ],
      "entry_id": "56327289_5633905_fact0",
      "score": 0.5767192840576172,
      "source_id": "56327289_5633905",
      "value": " Australia"
    },
    {
      "caught_by": [
        "semantic"
      ],
      "entry_id": "32310317_1612539_fact3",
      "score": 0.5750581622123718,
      "source_id": "32310317_1612539",
      "value": " Victoria"
    },
    {
      "caught_by": [
        "semantic"
      ],
      "entry_id": "35481682_1825239_fact1",
      "score": 0.5742583870887756,
      "source_id": "35481682_1825239",
      "value": " Victoria"
    },
    {
      "caught_by": [
        "semantic"
      ],
      "entry_id": "31849046_1237213_fact0",
      "score": 0.5740824341773987,
      "source_id": "31849046_1237213",
      "value": " the state of Victoria, Australia"
    },
    {
      "caught_by": [
        "semantic"
      ],
      "entry_id": "7122087_1036098_fact3",
      "score": 0.5724735856056213,
      "source_id": "7122087_1036098",
      "value": " Australia"
    },
    {
      "caught_by": [
        "semantic"
      ],
      "entry_id": "47087081_3723461_fact0",
      "score": 0.571864128112793,
      "source_id": "47087081_3723461",
      "value": " Australian state of Victoria"
    },
    {
      "caught_by": [
        "semantic"
      ],
      "entry_id": "33020142_2186528_fact3",
      "score": 0.5713144540786743,
      "source_id": "33020142_2186528",
      "value": " Victoria"
    },
    {
      "caught_by": [
        "semantic"
      ],
      "entry_id": "35942828_2209127_fact1",
      "score": 0.5708822011947632,
      "source_id": "35942828_2209127",
      "value": " Victoria"
    },
    {
      "caught_by": [
        "semantic"
      ],
      "entry_id": "14168077_1709860_fact3",
      "score": 0.570729672908783,
      "source_id": "14168077_1709860",
      "value": " Australian state of Victoria"
    },
    {
      "caught_by": [
        "semantic"
      ],
      "entry_id": "39424849_5055917_fact2",
      "score": 0.570726752281189,
      "source_id": "39424849_5055917",
      "value": " British colony of Victoria"
    },
    {
      "caught_by": [
        "semantic"
      ],
      "entry_id": "1211430_705953_fact1",
      "score": 0.5698385834693909,
      "source_id": "1211430_705953",
      "value": ", Australia"
    },
    {
      "caught_by": [
        "semantic"
      ],
      "entry_id": "41048360_3970096_fact0",
      "score": 0.5695837140083313,
      "source_id": "41048360_3970096",
      "value": " Victoria"
    },
    {
      "caught_by": [
        "semantic"
      ],
      "entry_id": "7596126_1465741_fact3",
      "score": 0.5693808197975159,
      "source_id": "7596126_1465741",
      "value": " Australian state of Victoria"
    },
    {
      "caught_by": [
        "semantic"
      ],
      "entry_id": "1975917_81532_fact2",
      "score": 0.5669123530387878,
      "source_id": "1975917_81532",
      "value": " Victoria"
    },
    {
      "caught_by": [
        "semantic"
      ],
      "entry_id": "51514859_4687920_fact1",
      "score": 0.5600355863571167,
      "source_id": "51514859_4687920",
      "value": " Victoria"
    },
    {
      "caught_by": [
        "semantic"
      ],
      "entry_id": "14887419_2436865_fact1",
      "score": 0.5575655102729797,
      "source_id": "14887419_2436865",
      "value": " British colony of Victoria (Australia)."
    },
    {
      "caught_by": [
        "semantic"
      ],
      "entry_id": "15907128_3374553_fact3",
      "score": 0.5554221868515015,
      "source_id": "15907128_3374553",
      "value": " Victoria"
    },
    {
      "caught_by": [
        "semantic"
      ],
      "entry_id": "13816502_1372109_fact1",
      "score": 0.5549528002738953,
      "source_id": "13816502_1372109",
      "value": " Australia"
    },
    {
      "caught_by": [
        "semantic"
      ],
      "entry_id": "1819774_914636_fact3",
      "score": 0.5534220933914185,
      "source_id": "1819774_914636",
      "value": " Australia"
    },
    {
      "caught_by": [
        "semantic"
      ],
      "entry_id": "27484742_2208822_fact4",
      "score": 0.5527071952819824,
      "source_id": "27484742_2208822",
      "value": " Australia"
    },
    {
      "caught_by": [
        "semantic"
      ],
      "entry_id": "39265564_4902429_fact1",
      "score": 0.5524580478668213,
      "source_id": "39265564_4902429",
      "value": " Australian state of Victoria"
    },
    {
      "caught_by": [
        "semantic"
      ],
      "entry_id": "68884790_4834027_fact1",
      "score": 0.5495327115058899,
      "source_id": "68884790_4834027",
      "value": " Australia"
    },
    {
      "caught_by": [
        "semantic"
      ],
      "entry_id": "17077172_1949910_fact1",
      "score": 0.5493053197860718,
      "source_id": "17077172_1949910",
      "value": " Australia"
    },
    {
      "caught_by": [
        "semantic"
      ],
      "entry_id": "48548871_4863003_fact2",
      "score": 0.5490756630897522,
      "source_id": "48548871_4863003",
      "value": " Australia"
    },
    {
      "caught_by": [
        "semantic"
      ],
      "entry_id": "2134493_353498_fact1",
      "score": 0.5489335060119629,
      "source_id": "2134493_353498",
      "value": " Victoria"
    },
    {
      "caught_by": [
        "semantic"
      ],
      "entry_id": "69135728_4977841_fact1",
      "score": 0.5483665466308594,
      "source_id": "69135728_4977841",
      "value": " Australia"
    },
    {
      "caught_by": [
        "semantic"
      ],
      "entry_id": "2012063_146443_fact101",
      "score": 0.5476913452148438,
      "source_id": "2012063_146443",
      "value": " Australia"
    },
    {
      "caught_by": [
        "semantic"
      ],
      "entry_id": "14860304_2411220_fact8",
      "score": 0.5439420938491821,
      "source_id": "14860304_2411220",
      "value": " Victoria"
    },
    {
      "caught_by": [
        "semantic"
      ],
      "entry_id": "40827729_3771335_fact1",
      "score": 0.5432746410369873,
      "source_id": "40827729_3771335",
      "value": " Australia"
    },
    {
      "caught_by": [
        "semantic"
      ],
      "entry_id": "39157844_4797316_fact1",
      "score": 0.5421825647354126,
      "source_id": "39157844_4797316",
      "value": " Australian state of Victoria"
    },
    {
      "caught_by": [
        "semantic"
      ],
      "entry_id": "35773908_2067158_fact1",
      "score": 0.5418799519538879,
      "source_id": "35773908_2067158",
      "value": " Australian state of Victoria"
    },
    {
      "caught_by": [
        "semantic"
      ],
      "entry_id": "39184448_4821039_fact1",
      "score": 0.5413291454315186,
      "source_id": "39184448_4821039",
      "value": " Australian state of Victoria"
    },
    {
      "caught_by": [
        "semantic"
      ],
      "entry_id": "40827565_3771109_fact1",
      "score": 0.5409237146377563,
      "source_id": "40827565_3771109",
      "value": " Australia"
    },
    {
      "caught_by": [
        "semantic"
      ],
      "entry_id": "53684920_3766431_fact259",
      "score": 0.5372815132141113,
      "source_id": "53684920_3766431",
      "value": " Victoria"
    },
    {
      "caught_by": [
        "semantic"
      ],
      "entry_id": "38660833_4356137_fact3",
      "score": 0.5367708802223206,
      "source_id": "38660833_4356137",
      "value": " Victoria"
    },
    {
      "caught_by": [
        "semantic"
      ],
      "entry_id": "10013740_2001910_fact1",
      "score": 0.5352175831794739,
      "source_id": "10013740_2001910",
      "value": " Australia"
    },
    {
      "caught_by": [
        "semantic"
      ],
      "entry_id": "48557680_4872303_fact0",
      "score": 0.5337113738059998,
      "source_id": "48557680_4872303",
      "value": " Australia"
    },
    {
      "caught_by": [
        "semantic"
      ],
      "entry_id": "40827121_3770600_fact1",
      "score": 0.5334814786911011,
      "source_id": "40827121_3770600",
      "value": " Australia"
    },
    {
      "caught_by": [
        "semantic"
      ],
      "entry_id": "6055183_288380_fact1",
      "score": 0.5315099954605103,
      "source_id": "6055183_288380",
      "value": " Australia"
    },
    {
      "caught_by": [
        "semantic"
      ],
      "entry_id": "14888780_2438106_fact1",
      "score": 0.5314201712608337,
      "source_id": "14888780_2438106",
      "value": " Australian state of Victoria"
    },
    {
      "caught_by": [
        "semantic"
      ],
      "entry_id": "14887238_2436519_fact1",
      "score": 0.5307046175003052,
      "source_id": "14887238_2436519",
      "value": " Australian state of Victoria"
    },
    {
      "caught_by": [
        "semantic"
      ],
      "entry_id": "5667389_1060816_fact2",
      "score": 0.5299344062805176,
      "source_id": "5667389_1060816",
      "value": " Australia"
    },
    {
      "caught_by": [
        "semantic"
      ],
      "entry_id": "40827678_3771300_fact1",
      "score": 0.5296170711517334,
      "source_id": "40827678_3771300",
      "value": " Australia"
    },
    {
      "caught_by": [
        "semantic"
      ],
      "entry_id": "45202855_5017764_fact116",
      "score": 0.5295702815055847,
      "source_id": "45202855_5017764",
      "value": " Victoria"
    },
    {
      "caught_by": [
        "semantic"
      ],
      "entry_id": "3751000_401868_fact117",
      "score": 0.5294610261917114,
      "source_id": "3751000_401868",
      "value": " Australia"
    },
    {
      "caught_by": [
        "semantic"
      ],
      "entry_id": "38100753_3881173_fact2",
      "score": 0.5284684300422668,
      "source_id": "38100753_3881173",
      "value": " Australian colony of Victoria"
    },
    {
      "caught_by": [
        "semantic"
      ],
      "entry_id": "283442_6031978_fact1",
      "score": 0.5277211666107178,
      "source_id": "283442_6031978",
      "value": " state of Victoria, Australia"
    },
    {
      "caught_by": [
        "semantic"
      ],
      "entry_id": "579457_1115205_fact2",
      "score": 0.5277054309844971,
      "source_id": "579457_1115205",
      "value": " Australia"
    },
    {
      "caught_by": [
        "semantic"
      ],
      "entry_id": "42369789_5131631_fact3",
      "score": 0.5256184339523315,
      "source_id": "42369789_5131631",
      "value": " Australia"
    },
    {
      "caught_by": [
        "semantic"
      ],
      "entry_id": "42568158_5307856_fact4",
      "score": 0.5252444744110107,
      "source_id": "42568158_5307856",
      "value": " Australia"
    },
    {
      "caught_by": [
        "semantic"
      ],
      "entry_id": "41870288_4701989_fact0",
      "score": 0.5248298048973083,
      "source_id": "41870288_4701989",
      "value": " Australia"
    },
    {
      "caught_by": [
        "semantic"
      ],
      "entry_id": "391485_6052889_fact1",
      "score": 0.5239709615707397,
      "source_id": "391485_6052889",
      "value": " Victoria"
    },
    {
      "caught_by": [
        "semantic"
      ],
      "entry_id": "14887096_2436364_fact2",
      "score": 0.5235315561294556,
      "source_id": "14887096_2436364",
      "value": " Australian state of Victoria"
    },
    {
      "caught_by": [
        "semantic"
      ],
      "entry_id": "14919238_2467247_fact1",
      "score": 0.5233914256095886,
      "source_id": "14919238_2467247",
      "value": " Australian state of Victoria"
    },
    {
      "caught_by": [
        "semantic"
      ],
      "entry_id": "42358822_5122130_fact3",
      "score": 0.5233257412910461,
      "source_id": "42358822_5122130",
      "value": " Australia"
    },
    {
      "caught_by": [
        "semantic"
      ],
      "entry_id": "42541778_5284677_fact4",
      "score": 0.5222814083099365,
      "source_id": "42541778_5284677",
      "value": " Australia"
    },
    {
      "caught_by": [
        "semantic"
      ],
      "entry_id": "21617185_1492476_fact1",
      "score": 0.5210898518562317,
      "source_id": "21617185_1492476",
      "value": " Australia"
    },
    {
      "caught_by": [
        "semantic"
      ],
      "entry_id": "69135767_4977864_fact1",
      "score": 0.5206888318061829,
      "source_id": "69135767_4977864",
      "value": " Australia"
    },
    {
      "caught_by": [
        "semantic"
      ],
      "entry_id": "14889194_2438360_fact1",
      "score": 0.5200536251068115,
      "source_id": "14889194_2438360",
      "value": " Australian state of Victoria"
    },
    {
      "caught_by": [
        "semantic"
      ],
      "entry_id": "39056777_4705343_fact2",
      "score": 0.5197411179542542,
      "source_id": "39056777_4705343",
      "value": " Australian state of Victoria"
    },
    {
      "caught_by": [
        "semantic"
      ],
      "entry_id": "21844713_1725804_fact0",
      "score": 0.5192327499389648,
      "source_id": "21844713_1725804",
      "value": " the United Kingdom and Victoria"
    },
    {
      "caught_by": [
        "semantic"
      ],
      "entry_id": "36794193_2908154_fact3",
      "score": 0.5188788771629333,
      "source_id": "36794193_2908154",
      "value": " Victoria"
    },
    {
      "caught_by": [
        "semantic"
      ],
      "entry_id": "57764509_4345140_fact0",
      "score": 0.5178411602973938,
      "source_id": "57764509_4345140",
      "value": " state of Victoria, Australia"
    },
    {
      "caught_by": [
        "semantic"
      ],
      "entry_id": "3025876_623779_fact71",
      "score": 0.5177297592163086,
      "source_id": "3025876_623779",
      "value": " Australia"
    },
    {
      "caught_by": [
        "semantic"
      ],
      "entry_id": "5377868_814750_fact2",
      "score": 0.5156043767929077,
      "source_id": "5377868_814750",
      "value": " Australia"
    },
    {
      "caught_by": [
        "semantic"
      ],
      "entry_id": "1864451_1008461_fact40",
      "score": 0.5155881643295288,
      "source_id": "1864451_1008461",
      "value": " Victoria"
    },
    {
      "caught_by": [
        "semantic"
      ],
      "entry_id": "22811966_2617795_fact3",
      "score": 0.5152090787887573,
      "source_id": "22811966_2617795",
      "value": " Australia"
    },
    {
      "caught_by": [
        "semantic"
      ],
      "entry_id": "39125045_4769102_fact1",
      "score": 0.5148640871047974,
      "source_id": "39125045_4769102",
      "value": " Australian colony of Victoria"
    },
    {
      "caught_by": [
        "semantic"
      ],
      "entry_id": "40709106_3663297_fact1",
      "score": 0.5144118070602417,
      "source_id": "40709106_3663297",
      "value": " Australia"
    },
    {
      "caught_by": [
        "semantic"
      ],
      "entry_id": "40714684_3668127_fact4",
      "score": 0.5131280422210693,
      "source_id": "40714684_3668127",
      "value": " Australia"
    },
    {
      "caught_by": [
        "semantic"
      ],
      "entry_id": "40709205_3663362_fact2",
      "score": 0.5122342109680176,
      "source_id": "40709205_3663362",
      "value": " Australia"
    },
    {
      "caught_by": [
        "semantic"
      ],
      "entry_id": "28123996_2773971_fact15",
      "score": 0.5119039416313171,
      "source_id": "28123996_2773971",
      "value": "Australia"
    },
    {
      "caught_by": [
        "semantic"
      ],
      "entry_id": "39349499_4979984_fact1",
      "score": 0.5117862820625305,
      "source_id": "39349499_4979984",
      "value": " the Australian state of Victoria"
    },
    {
      "caught_by": [
        "semantic"
      ],
      "entry_id": "39204290_4840243_fact1",
      "score": 0.5110623240470886,
      "source_id": "39204290_4840243",
      "value": " Australian state of Victoria"
    },
    {
      "caught_by": [
        "semantic"
      ],
      "entry_id": "29662319_1651882_fact0",
      "score": 0.5103675127029419,
      "source_id": "29662319_1651882",
      "value": " Australia"
    },
    {
      "caught_by": [
        "semantic"
      ],
      "entry_id": "40827487_3771086_fact1",
      "score": 0.51021808385849,
      "source_id": "40827487_3771086",
      "value": " Australia"
    },
    {
      "caught_by": [
        "semantic"
      ],
      "entry_id": "36530436_2681558_fact1",
      "score": 0.5099414587020874,
      "source_id": "36530436_2681558",
      "value": " Australian state of Victoria"
    },
    {
      "caught_by": [
        "semantic"
      ],
      "entry_id": "14887284_2436567_fact1",
      "score": 0.5084384679794312,
      "source_id": "14887284_2436567",
      "value": " Australian state of Victoria"
    },
    {
      "caught_by": [
        "semantic"
      ],
      "entry_id": "24612319_2052211_fact1",
      "score": 0.5083392858505249,
      "source_id": "24612319_2052211",
      "value": " Australian colony of Victoria"
    },
    {
      "caught_by": [
        "semantic"
      ],
      "entry_id": "42604758_5337487_fact5",
      "score": 0.5081687569618225,
      "source_id": "42604758_5337487",
      "value": " Australia"
    },
    {
      "caught_by": [
        "semantic"
      ],
      "entry_id": "40827361_3770959_fact1",
      "score": 0.506280779838562,
      "source_id": "40827361_3770959",
      "value": " Australia"
    },
    {
      "caught_by": [
        "semantic"
      ],
      "entry_id": "39087289_4731912_fact1",
      "score": 0.5049824118614197,
      "source_id": "39087289_4731912",
      "value": " Australian state of Victoria"
    },
    {
      "caught_by": [
        "semantic"
      ],
      "entry_id": "40825956_3769757_fact1",
      "score": 0.5049121975898743,
      "source_id": "40825956_3769757",
      "value": " Australia"
    },
    {
      "caught_by": [
        "semantic"
      ],
      "entry_id": "2134400_353364_fact2",
      "score": 0.5049057006835938,
      "source_id": "2134400_353364",
      "value": " Victoria"
    }
  ],
  "envelope_top_k": 500,
  "example_key": "3096e768-0d9f-425f-9190-44d5d8e2593a",
  "index_nprobe": null,
  "manifest_id": "1a6c15613d5230ff",
  "margin": 0.2850016951560974,
  "max_closure_size": 10000,
  "predicates_active": [
    "geometric",
    "semantic"
  ],
  "radius": 0.85,
  "s_del": 0.9443220496177673,
  "s_surv": 0.6593203544616699,
  "source_ids": [],
  "strategy": "closure",
  "top_survivors": [
    {
      "entry_id": "56265345_5590425_fact1",
      "score": 0.6593203544616699,
      "source_id": "56265345_5590425",
      "value": " the Australian Capital Territory"
    },
    {
      "entry_id": "15224595_2745086_fact2",
      "score": 0.6465262174606323,
      "source_id": "15224595_2745086",
      "value": " Western Australia"
    },
    {
      "entry_id": "48994460_5246072_fact0",
      "score": 0.6363001465797424,
      "source_id": "48994460_5246072",
      "value": " Australian"
    },
    {
      "entry_id": "49004657_5254925_fact0",
      "score": 0.6342676281929016,
      "source_id": "49004657_5254925",
      "value": " Australian"
    },
    {
      "entry_id": "48920262_5187088_fact0",
      "score": 0.6291494369506836,
      "source_id": "48920262_5187088",
      "value": " Australian"
    }
  ],
  "truncated": false
}